AUTHORS.md
CHANGES.txt
LICENSE.txt
MANIFEST.in
README.md
README.rst
setup.py
pandasql/__init__.py
pandasql/sqldf.py
pandasql/data/births.csv
pandasql/data/births_by_month.csv
pandasql/data/meat.csv
pandasql/tests/__init__.py
pandasql/tests/test_pandasql.py
pandasql/tests/test_utils.py
pandasql_lts.egg-info/PKG-INFO
pandasql_lts.egg-info/SOURCES.txt
pandasql_lts.egg-info/dependency_links.txt
pandasql_lts.egg-info/requires.txt
pandasql_lts.egg-info/top_level.txt