Metadata-Version: 2.1
Name: pandasql-lts
Version: 0.7.3
Summary: sqldf for pandas
Home-page: https://github.com/BuiHoangTu/pandasql/tree/release
Author: Greg Lamp
Author-email: greg@yhathq.com
Maintainer: Bui Hoang Tu
Maintainer-email: bhtu.work@gmail.com
License: MIT
Classifier: License :: OSI Approved :: MIT License
License-File: LICENSE.txt
License-File: AUTHORS.md
Requires-Dist: numpy
Requires-Dist: pandas
Requires-Dist: sqlalchemy
